chatshit/__init__.py
chatshit/__main__.py
chatshit/app.py
chatshit/network/chatroom_server.py
chatshit/network/client.py
chatshit/network/proto.py
chatshit/screens/chatroom_screen.py
chatshit/screens/client_screen.py
chatshit/screens/confirmation_screen.py
chatshit/screens/create_server_screen.py
chatshit/screens/delete_message_screen.py
chatshit/screens/home_screen.py
chatshit/screens/login_screen.py
chatshit/styles.css
chatshit/widgets/chat_list.py
chatshit/widgets/member_list.py
chatshit/widgets/message_list.py
chatshit/widgets/server_list.py
chatshit-0.1.0.dist-info/METADATA
chatshit-0.1.0.dist-info/WHEEL
chatshit-0.1.0.dist-info/entry_points.txt
chatshit-0.1.0.dist-info/RECORD
